rest_framework_access_key/__init__.py
rest_framework_access_key/admin.py
rest_framework_access_key/apps.py
rest_framework_access_key/authentication.py
rest_framework_access_key/models.py
rest_framework_access_key/settings.py
rest_framework_access_key/migrations/0001_initial.py
rest_framework_access_key/migrations/__init__.py
drf_access_key-0.1.0.dist-info/LICENSE
drf_access_key-0.1.0.dist-info/METADATA
drf_access_key-0.1.0.dist-info/WHEEL
drf_access_key-0.1.0.dist-info/top_level.txt
drf_access_key-0.1.0.dist-info/RECORD
