Metadata-Version: 2.1
Name: drf-access-key
Version: 0.1.0
Summary: A library that provides a simple Access Key & Secret Key authorization for Django REST framework.
Home-page: https://github.com/ZhaoQi99/drf-access-key
Author: Qi Zhao
Author-email: zhaoqi99@outlook.com
License: UNKNOWN
Project-URL: Homepage, https://github.com/ZhaoQi99/drf-access-key
Project-URL: Changelog, https://github.com/ZhaoQi99/drf-access-key/releases
Project-URL: Source, https://github.com/ZhaoQi99/drf-access-key
Project-URL: Issue Tracker, https://github.com/ZhaoQi99/drf-access-key/issues
Keywords: AccessKey,Django-REST-framework,django-access-key
Platform: UNKNOWN
Classifier: License :: OSI Approved :: GNU General Public License v3 (GPLv3)
Classifier: Programming Language :: Python :: 3
Classifier: Programming Language :: Python :: 3.6
Classifier: Programming Language :: Python :: 3.7
Classifier: Programming Language :: Python :: 3.8
Classifier: Programming Language :: Python :: 3.9
Classifier: Programming Language :: Python :: 3.10
Classifier: Framework :: Django :: 2
Classifier: Framework :: Django :: 3
Classifier: Framework :: Django :: 4
Classifier: Programming Language :: Python :: Implementation :: CPython
Requires-Python: >=3.6
License-File: LICENSE
Requires-Dist: Django (>=2.0)
Requires-Dist: djangorestframework
